prprint/__init__.py
prprint/prprint.py
prprint-0.1.1.dist-info/METADATA
prprint-0.1.1.dist-info/WHEEL
prprint-0.1.1.dist-info/top_level.txt
prprint-0.1.1.dist-info/RECORD
