Metadata-Version: 2.1
Name: prprint
Version: 0.1.1
Summary: An enhanced pprint module with additional features.
Home-page: https://github.com/LovelyCobra/prprint
Author: Lovely Cobra
Author-email: elene.yeti@web.de
Classifier: Programming Language :: Python :: 3
Classifier: License :: OSI Approved :: MIT License
Classifier: Operating System :: OS Independent
Requires-Python: >=3.7
